objettoqt/__init__.py
objettoqt/_mixins.py
objettoqt/_objects.py
objettoqt/mixins.py
objettoqt/models.py
objettoqt/objects.py
objettoqt/views.py
objettoqt/widgets.py
objettoqt/_models/__init__.py
objettoqt/_models/list.py
objettoqt/_views/__init__.py
objettoqt/_views/list.py
objettoqt/_widgets/__init__.py
objettoqt/_widgets/history.py
objettoqt/_widgets/list.py
objettoqt/_widgets/widget.py
objettoqt-0.3.1.dist-info/LICENSE
objettoqt-0.3.1.dist-info/METADATA
objettoqt-0.3.1.dist-info/WHEEL
objettoqt-0.3.1.dist-info/top_level.txt
objettoqt-0.3.1.dist-info/RECORD
