Metadata-Version: 2.1
Name: objettoqt
Version: 0.3.1
Summary: Utilities to use Objetto with Qt
Home-page: https://github.com/brunonicko/objettoqt
Author: Bruno Nicko
Author-email: brunonicko@gmail.com
License: UNKNOWN
Platform: UNKNOWN
Classifier: Intended Audience :: Developers
Classifier: License :: OSI Approved :: MIT License
Classifier: Operating System :: OS Independent
Classifier: Programming Language :: Python :: 2.7
Classifier: Programming Language :: Python :: 3.5
Classifier: Programming Language :: Python :: 3.6
Classifier: Programming Language :: Python :: 3.7
Classifier: Programming Language :: Python :: 3.8
Classifier: Programming Language :: Python :: 3.9
Classifier: Programming Language :: Python :: Implementation :: PyPy
Requires-Python: >=2.7
Requires-Dist: pyrsistent
Requires-Dist: qualname
Requires-Dist: six
Requires-Dist: slotted
Requires-Dist: enum34 ; python_version < "3.4"
